{
  "locale": "si",
  "description": "අලුත් පක්ෂයක්. මේ දවස්වල හැමෝම කතා කරන මාතෘකාවක්. ඒ තමයි අපි හැමෝටම සිටගත හැකි නව දේශපාලන ව්‍යාපාරයක්. සම්ප්‍රදායෙන් ඔබ්බට ගිය නව දේශපාලන ප්‍රවිශ්ටයක් රටට හදුන්වාදීමට අප කැපවී සිටින්නෙමු. මේ එහි දිහහැරුමක එක් පැතිකඩකි.",
  "header": "අලුත් පක්ෂයක්",
  "MainButtonText": "අපි ගැන",
  "SecondaryTitle": "ජාතික ප්‍රජාතන්ත්‍රවාදී පෙරමුණ",
  "SecondaryParagraph": "සාම්ප්‍රදායික හුදු දේශපාලන පක්ෂ වලින් ඔබ්බට දිවෙන ජාතික ප්‍රජාතන්ත්‍රවාදී පෙරමුණේ මූලික අරමුණ සමෘද්ධිමත් ශ්‍රී ලංකාවක් බිහිකරලීම. ඒ වෙනුවෙන් මහජනතාව වෙනුවෙන් සියලු වරදාන වරප්‍රසාද ප්‍රතික්ෂේප කරමින් මහජන සේවයට කැපවීමට අප බැදී සිටිමු. අතීතයේ ජාතික නායකයින්ගෙන් පසු මෙරටින් මැකී ගිය 'මහත්මා දේශපාලනය' අපි යළි මව්බිමට කැන්දන්නෙමු.",
  "pointTitle": "ඒ වෙනුවෙන් අප පහත කැපකිරීම් කිරීමට බැදී සිටින්නෙමු.",
  "commitmentPara": "එකී කැපකිරීම් කරමින් ජනතා හිත සුව පිණිස සබුද්ධිකවාදී, නිර්මාණශීලී, ප්‍රායෝගික, ක්‍රමවත් වැඩපිළිවෙළක් තුළින් වත්මන් ආර්ථික අර්බුදය ජයගෙන ඔබගේත්, මාගේත් මාතෘභූමිය ලෝකයේ ප්‍රබුද්ධ රාජ්‍යයක් බවත් පත්කිරීමට අප කැපවී සිටිමු. ",
  "welcometitle": "Welcome to the Party",
  "welcomedesc": "එකතුවෙමු. එක්ව වැඩ කරමු. අභියෝග ජයගනිමින් සමෘද්ධිමත් දේශයක් ගොඩනැගීමට කැපවෙමු. මේ ආරාධනය ඒ වෙනුවෙන්මයි.",
  "obligations": "Our Obligations",
  "obligationsesc": "Lorem ipsum dolor sit amet, consectetur adipiscing elit. Vestibulum sapien ligula, viverra eu enim nec, pulvinar hendrerit sem. Aliquam sit",
  "newstitle": "පුවත්පත් නිවේදන",
  "contactus": "අප අමතන්න",
  "contactdescription":"ඔබගේ විද්‍යුත් තැපෑල තබන්න, අපි පැය 24ක් ඇතුළත ඔබ වෙත ආපසු එන්නෙමු",
  "sendamessage":"අපට පණිවිඩයක් එවන්න",
  "socialfeed":"අපගේ Facebook පිටුව සමඟ සම්බන්ධ වෙන්න.",
  "submitform":"ඔබගේ පණිවිඩය අප වෙත ලැබුණි. ",
  "submitformdesc":"අපි කඩිනමින් නැවත ඔබ වෙත ප්‍රතිචාර දක්වන්නෙමු.",
  "sendmsg":"පණිවිඩය යවන්න ",
  "memberformsubmission":"ඔබගේ ඉදිරිපත් කිරීම අපට ලැබුණි.",
  "memberformdesc":"ඔබගේ පැතිකඩ වෙත ප්‍රවේශ වීමට අපි ඔබට QR කේතය සහිත විද්‍යුත් තැපෑලක් එවන්නෙමු.",
  "submitanotherresponse":"වෙනත් ප්‍රතිචාරයක් ඉදිරිපත් කරන්න",
  "msgform":[
    "ඔබගේ ඊමේල් ලිපිනය",
    "ඔබගේ නම",
    "පණිවිඩය",
    "විෂය"
  ],
  "PointDetails": [
    {
      "key": 1,
      "point": "මන්ත්‍රීවරුන්ට හිමි වැටුප ලබා නොගැනීම.",
      "desecription": "සෑම මහජන මන්ත්‍රීවරයෙකුටම මන්ත්‍රී ධූරයට අදාළ වැටුපක් රජය මඟින් ගෙවන අතර, විශ්‍රාම වැටුපක් ද ලබාදීමට කටයුතු කරයි. නමුත් අප පක්ෂයේ කිසිදු මන්ත්‍රීවරයෙකු වැටුප් නොලබා තම ⁣සේවය ජනතාව වෙත ඉටු කිරීමට බැදී සිටියි. එහි පරම අරමුණ මහජන මුදලින් නඩත්තු නොවන ජනතා සේවයක් බිහිකරලීමයි."
    },
    {
      "key": 2,
      "point": "ඉන්ධන දීමනාව, දුරකථන දීමනාව, කාර්යාල දීමනාව, මුද්දර දීමනාව ඇතුළු සියලුම දීමනා ප්‍රතික්ෂේප කිරීම.",
      "desecription": "විශේෂයෙන් පාර්ලිමේන්තු සහ පළාත් සභා මන්ත්‍රීවරුන්ට මෙන්ම පලාත් පාලන නියෝජිතන්ටද විවිධ දීමනා හිමිවන අතර, එම දීමනා සියල්ල ලබා දෙන්නේ මෙරට බදු ගෙවන ජනතාව බව නොරහසකි. මෙරට බදු ගෙවන ජනතාව තවදුරටත් මහජන නියෝජිතයන් නඩත්තු කළ යුතුද.? නැත. දේශපාලනය ගරු සේවයක් විය යුතුය. එබැවින් මන්ත්‍රීවරුන් සඳහා හිමිවන ඉන්ධන දීමනාව, දුරකථන දීමනාව, කාර්යාල දීමනාව, මුද්දර දීමනාව ඇතුළු සියලුම දීමනා අප පක්ෂය විසින් ප්‍රතික්ෂේප කරනු ලබයි."
    },
    {
      "key": 3,
      "point": "රජයේ නිල නිවාස සහ බංගලා භුක්ති නොවිදීම.",
      "desecription": "අමාත්‍යවරුන්, රාජ්‍ය අමාත්‍යවරුන් සහ නියෝජ්‍ය අමාත්‍යවරුන් සඳහා හිමි වන රජයේ නිල නිවාස සහ බංගලා සියල්ලම අප පක්ෂයෙන් තේරී පත්වන මහජන නියෝජිතයන් විසින් ප්‍රතික්ෂේප කරනු ලබයි. ඇමතිවරුන්ගේ වැටුපෙන් එම බංගලා සඳහා අයකර ගනු ලබන්නේ ඉතා සුළු මුදලකි. එම නිල නිවාසයේ හෝ බංගලාවේ ජල බිල්පත්, විදුලි බිල්පත්, සියලු නඩත්තු කටයුතු සිදුකරනු ලබන්නේ අදාළ අමාත්‍යවරයාගේ අමාත්‍යාංශයේ අභ්‍යන්තර පාලන අංශය විසිනි. එ් සඳහා වියදම් කෙරෙන සියලු මුදල් මහජන මුදල් බැවින්, මහජන මුදලින් නඩත්තු නොවන අප පක්ෂය රජයේ නිල නිවාස සහ බංගලා ප්‍රතික්ෂේප කරන්නෙමු."
    },
    {
      "key": 4,
      "point": "පාර්ලිමේන්තු මන්ත්‍රීවරුන් සඳහා ලැබෙන තීරු බදු රහිත වාහන බලපත්‍රය ලබා නොගැනීම.",
      "desecription": "පාර්ලිමේන්තු මන්ත්‍රීවරුන් සඳහා ලැබෙන තවත් එක් දීමනාවක් ලෙස තීරු බදු රහිත වාහන බලපත්‍රය හැදින්විය හැක. රටේ මහජනතාව වෙනුවෙන් සේවය කිරීමට පත්ව, මහජනතාවට නොලැබෙන වරප්‍රසාද භුක්ති විදීමට අප පක්ෂය සූදානම් නැත. එබැවින් පාර්ලිමේන්තු මන්ත්‍රීවරුන් සඳහා ලැබෙන තීරු බදු රහිත වාහන බලපත්‍රය අප පක්ෂය ප්‍රතික්ෂේප කරන්නෙමු."
    },
    {
      "key": 5,
      "point": "ආරක්ෂාව වෙනුවෙන් ප්‍රභූ ආරක්ෂක නිලධාරීන්ගේ සහය ලබා නොගැනීම සහ ආරක්ෂාව ලබාගැනීම අත්‍යාවශ්‍ය නම්, ඒ සඳහා අදාළ මුදල රජයට ගෙවීම.",
      "desecription": "මහජනතාව ඉදිරියට යාමට ප්‍රභූ ආරක්ෂක නිලධාරීන් අපට අවශ්‍ය නැත. දූෂණ වංචා නොකර, ජනතා අභිලාෂයන් නිසියාකාරව ඉටුකරන්නේ නම් ප්‍රභූ ආරක්ෂාව අවශ්‍ය නොවේ. නමුත් ජීවිතයට තර්ජනයක් පවතීනම් පමණක් ප්‍රභූ ආරක්ෂාව ලබාගැනීමට කටයුතු කරන අතර, ඒ සඳහා අදාළ මුදල රජයට ගෙවීමට අප පක්ෂයෙන් පත්වන මහජන නියෝජිතයන් බැදී සිටී."
    },
    {
      "key": 6,
      "point": "පාර්ලිමේන්තුවේ ආපන ශාලාවෙන් කහට කෝප්පයක් වත් මහජන මුදලින් භුක්ති නොවිදීම.",
      "desecription": "පාර්ලිමේන්තුවේ ඇති ආපන ශාලාව සම්බන්ධයෙන් නොයෙකුත් කතාන්දර බට බැදී ඇති යුගයක, රටේ ජනතාව කුසට අහරක් නොමැතිව බඩගින්දර උසුලමින් ජීවිතය ගැටගසාගන්නා මොහොතක ඉතාමත් සුළු මුදලකට රජ බොජුන් පාර්ලිමේන්තු ආපන ශාලාවෙන් භුක්ති විදීමට අපට නොහැකිය. එබැවින් පාර්ලිමේන්තුවේ ආපන ශාලාවෙන් කහට කෝප්පයක් වත් මහජන මුදලින් භුක්ති නොවිදීමට අප පක්ෂය බැදී සිටී."
    },
    {
      "key": 7,
      "point": "රජයේ වාහන භාවිතා නොකිරීම.",
      "desecription": "අප පක්ෂයේ මහජන නියෝජිතයන් අමාත්‍ය තනතුරු, නියෝජ්‍ය අමාත්‍ය තනතුරු, රාජ්‍ය අමාත්‍ය තනතුරු හෝ වෙනත් ඕනෑම රජයේ තනතුරක් දරන්නේ නම්, ඒ වෙනුවෙන් හිමිවන රජයේ වාහන භාවිතා නොකිරීමට බැදී සිටී."
    },
    {
      "key": 8,
      "point": "දූෂිත දේශපාලඥයින් කිසිවෙකුට අප පක්ෂයෙන් මැතිවරණ සඳහා තරඟ වැදීමට නාම යෝජනා ලබා නොදීම හා භික්ෂූන් වහන්සේලාට සහ පූජ්‍ය පක්ෂයට නාම යෝජනා ලබා නොදීම",
      "desecription": "අධිකරණ හමුවේ වැරිදි කරුවෙකු ලෙස ඔප්පු වූ කිසිදු තැනැත්තෙකුට හෝ දූෂණ වංචා චෝදනා එල්ල වූ කිසිදු අයෙකුට අප පක්ෂයෙන් නාම යෝජනා ලබා නොදෙන අතර, ගෞරවණීය ස්වාමීන් වහන්සේලාට මෙන්ම පූජ්‍ය පක්ෂයේ කිසිඳු අයෙකුට අප පක්ෂය හරහා මැතිවරණයට ඉදිරිපත් වීමට නාම යෝජනා අපි ලබා නොදෙන්නෙමු."
    },
    {
      "key": 9,
      "point": "අප පක්ෂයේ සියලු මහජන මන්ත්‍රීවරුන්ගේ වත්කම් බැරකම් ප්‍රකාශ ප්‍රසිද්ධියට පත්කිරීම.",
      "desecription": "අප පක්ෂයේ සියලු මහජන මන්ත්‍රීවරුන්ගේ වත්කම් හා බැරකම් ප්‍රකාශ අප ප්‍රසිද්ධියට පත්කරන්නෙමු."
    },
    {
      "key": 10,
      "point": " මහජන මුදල් වැය කරමින් සිදුකරන විදේශ සංචාර ප්‍රතික්ෂේප කිරීම.",
      "desecription": "රාජතාන්ත්‍රික මට්මමෙන් සිදු කෙරෙන සියලුම විදේශ සංචාර මහජන මුදල් භාවිතා නොකොට අපගේ පෞද්ගලික වියදමින් ඒ සඳහා වැය වන සියලු වියදම් පියවීමට අප පක්ෂය බැදී සිටින්නෙමු."
    }
  ],
  "end": "සාර්ථක ව්‍යසායකත්වයෙන් සහ මනා කළමනාකාරිත්වයකින් ලෝකය දිනූ  දිරිය මිනිසුන්ගෙන් සමන්විත ජන පවුරකින් අපි දැනටමත් සවිමත්ව සිටිමු. ",
  "joinus": "ඔබත්, එක්වන්න!",
  "forthe": "මව්බිමේ හෙට දවස වෙනුවෙන්.",
  "joinusbtn":"පක්ෂ සාමාජිකත්වය ලබාගැනීම සඳහා"
  
}
